poddl/__init__.py
poddl/exceptions.py
poddl/lib.py
poddl/util.py
poddl-0.3.0.dist-info/LICENSE
poddl-0.3.0.dist-info/METADATA
poddl-0.3.0.dist-info/WHEEL
poddl-0.3.0.dist-info/entry_points.txt
poddl-0.3.0.dist-info/top_level.txt
poddl-0.3.0.dist-info/RECORD
