Metadata-Version: 2.1
Name: poddl
Version: 0.3.0
Summary: Downloads podcasts from RSS feeds
Home-page: https://github.com/benkyriakou/poddl
Author: Ben Kyriakou
Author-email: benkyriakou@users.noreply.github.com
License: MIT
Platform: UNKNOWN
Classifier: Development Status :: 4 - Beta
Classifier: License :: OSI Approved :: GNU General Public License v3 or later (GPLv3+)
Requires-Dist: requests
Requires-Dist: unidecode
